{"stat.useItem.351":113,"stat.craftItem.340":28,"stat.craftItem.69":1,"stat.useItem.355":3,"stat.craftItem.101":224,"stat.useItem.359":480,"stat.useItem.116":2,"stat.craftItem.61":2,"stat.horseOneCm":624,"stat.leaveGame":19,"stat.killEntity.Blaze":16,"stat.craftItem.339":84,"stat.useItem.362":62,"stat.mineBlock.14":55,"stat.mineBlock.13":76,"TwilightForest8":266,"stat.mineBlock.16":506,"stat.mineBlock.15":253,"TwilightForest6":78,"stat.craftItem.331":576,"stat.killEntity.PigZombie":85,"stat.mineBlock.18":17,"stat.swimOneCm":238425,"stat.climbOneCm":20289,"TwilightForest3":16,"stat.craftItem.76":1,"TwilightForest1":7,"TwilightForest2":4,"stat.craftItem.325":10,"achievement.exploreAllBiomes":{"value":0,"progress":["Twilight Highlands","Twilight Clearing","Sunflower Plains","Desert M","Roofed Forest","Birch Forest","Beach","Snowy Forest","River","Ocean","Taiga","Swampland","Birch Forest Hills","ForestHills","Twilight Stream","Plains","TaigaHills","Twilight Forest","Dense Twilight Forest","Enchanted Forest","Dark Forest","DesertHills","Firefly Forest","Forest","Desert","Deep Ocean","Savanna","Hell"]},"stat.mineBlock.12":1069,"stat.useItem.331":55,"stat.craftItem.362":4,"stat.useItem.338":10,"stat.mineBlock.4":5,"stat.mineBlock.5":1,"stat.mineBlock.3":239,"stat.mineBlock.1":299,"stat.mineBlock.112":44,"stat.killEntity.Enderman":1,"stat.mineBlock.113":2,"stat.craftItem.116":1,"stat.craftItem.359":5,"stat.mineBlock.116":1,"stat.flyOneCm":3445424,"stat.craftItem.351":114,"stat.craftItem.355":3,"stat.useItem.103":1,"stat.killEntity.Witch":1,"stat.useItem.107":10,"stat.killEntity.Bat":1,"ic2.acquireResin":82,"stat.craftItem.22":1,"stat.mineBlock.175":27,"stat.killEntity.Creeper":18,"stat.craftItem.35":1,"achievement.mineWood":55,"stat.killEntity.Squid":2,"stat.useItem.87":19,"stat.craftItem.47":25,"stat.useItem.85":165,"achievement.openInventory":1097,"stat.mineBlock.161":1,"stat.mineBlock.153":37,"stat.deaths":2,"stat.drop":490,"stat.playOneMinute":1277198,"stat.craftItem.50":144,"stat.killEntity.Sheep":8,"stat.craftItem.54":13,"stat.killEntity.Zombie":56,"stat.diveOneCm":153490,"stat.killEntity.Ghast":1,"stat.mineBlock.82":66,"stat.mineBlock.85":1,"stat.mineBlock.87":636,"stat.useItem.69":5,"stat.mineBlock.86":5,"stat.mineBlock.89":57,"stat.mineBlock.88":40,"stat.useItem.76":1,"stat.useItem.77":3,"stat.jump":7200,"stat.fallOneCm":1482293,"stat.useItem.70":3,"stat.breakItem.359":1,"stat.mineBlock.98":5,"stat.mineBlock.99":2,"stat.useItem.175":5,"stat.useItem.295":136,"stat.craftItem.5":384,"TwilightForest13":2,"stat.damageTaken":42465,"TwilightForest18":59,"TwilightForest17":35,"stat.useItem.47":25,"stat.useItem.49":20,"stat.useItem.54":68,"stat.useItem.50":21,"stat.damageDealt":99145,"stat.killEntity.Cow":31,"stat.killEntity.Pig":14,"stat.mineBlock.73":23,"stat.useItem.58":3,"stat.craftItem.261":1,"stat.mineBlock.47":20,"stat.useItem.21":6,"stat.craftItem.262":16,"stat.mineBlock.49":15,"stat.craftItem.143":1,"stat.mineBlock.48":1,"stat.walkOneCm":4970308,"stat.useItem.278":208,"stat.animalsBred":19,"stat.craftItem.388":7,"stat.useItem.283":5,"stat.mineBlock.44":1,"ic2.buildQArmor":3,"stat.mineBlock.100":4,"stat.mineBlock.103":8,"stat.useItem.39":1,"stat.mineBlock.50":3,"stat.mineBlock.54":2,"stat.useItem.291":186,"stat.useItem.37":12,"stat.mineBlock.56":6,"stat.useItem.38":19,"stat.useItem.293":16,"stat.mineBlock.24":1,"stat.killEntity.Skeleton":52,"stat.useItem.259":1,"stat.killEntity.Chicken":15,"stat.craftItem.280":64,"stat.killEntity.Spider":16,"stat.mobKills":343,"stat.mineBlock.21":16,"stat.useItem.383":35,"stat.mineBlock.38":14,"stat.useItem.12":1,"stat.useItem.143":1,"stat.mineBlock.37":13,"stat.craftItem.155":4,"stat.mineBlock.39":9,"stat.craftItem.278":1,"stat.useItem.1":11,"stat.useItem.4":56,"stat.useItem.5":4,"stat.useItem.3":724,"stat.useItem.391":123,"stat.mineBlock.32":1,"stat.mineBlock.31":25,"stat.useItem.272":5,"stat.useItem.392":234}